hello_rajnish_307_2020.py
hello_rajnish_307_2020-0.0.1.dist-info/LICENSE.txt
hello_rajnish_307_2020-0.0.1.dist-info/METADATA
hello_rajnish_307_2020-0.0.1.dist-info/WHEEL
hello_rajnish_307_2020-0.0.1.dist-info/top_level.txt
hello_rajnish_307_2020-0.0.1.dist-info/RECORD
